[
  {
    "atm_iv": 0.55558,
    "term_m1_m2": -10.46,
    "term_m1_m3": -4.69,
    "skew": 4.85,
    "iv_rank (HV)": 19.64720251831613,
    "iv_percentile (HV)": 42.438563327032135,
    "date": "2024-10-01"
  },
  {
    "atm_iv": 0.5429,
    "term_m1_m2": -10.97,
    "term_m1_m3": -5.79,
    "skew": 6.1,
    "iv_rank (HV)": 18.870281519490366,
    "iv_percentile (HV)": 39.50850661625709,
    "date": "2024-10-02"
  },
  {
    "atm_iv": 0.55956,
    "term_m1_m2": -10.88,
    "term_m1_m3": -4.91,
    "skew": 5.4,
    "iv_rank (HV)": 19.891062579461753,
    "iv_percentile (HV)": 42.53308128544423,
    "date": "2024-10-03"
  },
  {
    "atm_iv": 0.53682,
    "term_m1_m2": -12.68,
    "term_m1_m3": -6.47,
    "skew": 4.81,
    "iv_rank (HV)": 18.497751576835732,
    "iv_percentile (HV)": 38.09073724007561,
    "date": "2024-10-04"
  },
  {
    "atm_iv": 0.68798,
    "term_m1_m2": 6.44,
    "term_m1_m3": 8.6,
    "skew": 1.41,
    "iv_rank (HV)": 27.759532190597813,
    "iv_percentile (HV)": 67.3913043478261,
    "date": "2024-10-07"
  },
  {
    "atm_iv": 0.71159,
    "term_m1_m2": 6.69,
    "term_m1_m3": 10.18,
    "skew": -0.44,
    "iv_rank (HV)": 29.206149286991845,
    "iv_percentile (HV)": 73.34593572778829,
    "date": "2024-10-08"
  },
  {
    "atm_iv": 0.70323,
    "term_m1_m2": 5.45,
    "term_m1_m3": 9.01,
    "skew": 0.42,
    "iv_rank (HV)": 28.69392061584174,
    "iv_percentile (HV)": 70.22684310018904,
    "date": "2024-10-09"
  },
  {
    "atm_iv": 0.69778,
    "term_m1_m2": 5.94,
    "term_m1_m3": 8.71,
    "skew": 0.74,
    "iv_rank (HV)": 28.3599916376398,
    "iv_percentile (HV)": 68.99810964083176,
    "date": "2024-10-10"
  },
  {
    "atm_iv": 0.70267,
    "term_m1_m2": 6.83,
    "term_m1_m3": 9.57,
    "skew": 0.26,
    "iv_rank (HV)": 28.659608647439335,
    "iv_percentile (HV)": 70.03780718336485,
    "date": "2024-10-11"
  },
  {
    "atm_iv": 0.72198,
    "term_m1_m2": 7.52,
    "term_m1_m3": 10.38,
    "skew": -0.74,
    "iv_rank (HV)": 29.84275884360066,
    "iv_percentile (HV)": 74.10207939508507,
    "date": "2024-10-14"
  },
  {
    "atm_iv": 0.75568,
    "term_m1_m2": 9.56,
    "term_m1_m3": 13.18,
    "skew": -0.65,
    "iv_rank (HV)": 31.907604084959363,
    "iv_percentile (HV)": 76.84310018903592,
    "date": "2024-10-15"
  },
  {
    "atm_iv": 0.75513,
    "term_m1_m2": 9.48,
    "term_m1_m3": 13.29,
    "skew": -0.43,
    "iv_rank (HV)": 31.873904830278434,
    "iv_percentile (HV)": 76.65406427221171,
    "date": "2024-10-16"
  },
  {
    "atm_iv": 0.73096,
    "term_m1_m2": 8.34,
    "term_m1_m3": 12.22,
    "skew": 0.82,
    "iv_rank (HV)": 30.392975765482007,
    "iv_percentile (HV)": 74.66918714555766,
    "date": "2024-10-17"
  },
  {
    "atm_iv": 0.73135,
    "term_m1_m2": 8.72,
    "term_m1_m3": 12.5,
    "skew": 0.48,
    "iv_rank (HV)": 30.416871600619384,
    "iv_percentile (HV)": 74.66918714555766,
    "date": "2024-10-18"
  },
  {
    "atm_iv": 0.75947,
    "term_m1_m2": 11.15,
    "term_m1_m3": 14.96,
    "skew": 1.21,
    "iv_rank (HV)": 32.139822585397035,
    "iv_percentile (HV)": 77.31568998109641,
    "date": "2024-10-21"
  },
  {
    "atm_iv": 0.77249,
    "term_m1_m2": 10.62,
    "term_m1_m3": 15.73,
    "skew": 0.64,
    "iv_rank (HV)": 32.93757585075283,
    "iv_percentile (HV)": 78.26086956521739,
    "date": "2024-10-22"
  },
  {
    "atm_iv": 0.77437,
    "term_m1_m2": 11.83,
    "term_m1_m3": 16.59,
    "skew": 1.85,
    "iv_rank (HV)": 33.052766030389456,
    "iv_percentile (HV)": 78.35538752362949,
    "date": "2024-10-23"
  },
  {
    "atm_iv": 0.80497,
    "term_m1_m2": 14.19,
    "term_m1_m3": 18.5,
    "skew": 2.69,
    "iv_rank (HV)": 34.92767001809202,
    "iv_percentile (HV)": 82.32514177693761,
    "date": "2024-10-24"
  },
  {
    "atm_iv": 0.81961,
    "term_m1_m2": 15.04,
    "term_m1_m3": 20.3,
    "skew": 1.65,
    "iv_rank (HV)": 35.82468290632619,
    "iv_percentile (HV)": 82.98676748582231,
    "date": "2024-10-25"
  },
  {
    "atm_iv": 0.86049,
    "term_m1_m2": 18.38,
    "term_m1_m3": 22.98,
    "skew": 1.48,
    "iv_rank (HV)": 38.32945659970137,
    "iv_percentile (HV)": 84.12098298676749,
    "date": "2024-10-28"
  },
  {
    "atm_iv": 0.89498,
    "term_m1_m2": 20.46,
    "term_m1_m3": 26.12,
    "skew": 1.46,
    "iv_rank (HV)": 40.44270622505633,
    "iv_percentile (HV)": 86.48393194706995,
    "date": "2024-10-29"
  },
  {
    "atm_iv": 0.96561,
    "term_m1_m2": 23.63,
    "term_m1_m3": 31.08,
    "skew": -0.68,
    "iv_rank (HV)": 44.770303239809,
    "iv_percentile (HV)": 87.52362948960302,
    "date": "2024-10-30"
  },
  {
    "atm_iv": 0.7188,
    "term_m1_m2": 7.99,
    "term_m1_m3": 11.92,
    "skew": 2.42,
    "iv_rank (HV)": 29.647915880172743,
    "iv_percentile (HV)": 73.91304347826086,
    "date": "2024-10-31"
  },
  {
    "atm_iv": 0.64598,
    "term_m1_m2": 5.77,
    "term_m1_m3": 7.94,
    "skew": 0.05,
    "iv_rank (HV)": 25.186134560417823,
    "iv_percentile (HV)": 60.113421550094515,
    "date": "2024-11-01"
  },
  {
    "atm_iv": 0.5745,
    "term_m1_m2": 2.09,
    "term_m1_m3": -0.86,
    "skew": 1.12,
    "iv_rank (HV)": 20.806456879340075,
    "iv_percentile (HV)": 45.17958412098299,
    "date": "2024-11-04"
  },
  {
    "atm_iv": 0.59179,
    "term_m1_m2": 2.49,
    "term_m1_m3": -0.48,
    "skew": 1.42,
    "iv_rank (HV)": 21.865838903764168,
    "iv_percentile (HV)": 48.39319470699433,
    "date": "2024-11-05"
  },
  {
    "atm_iv": 0.574,
    "term_m1_m2": 2.18,
    "term_m1_m3": -1.22,
    "skew": -0.82,
    "iv_rank (HV)": 20.775821193266495,
    "iv_percentile (HV)": 45.17958412098299,
    "date": "2024-11-06"
  },
  {
    "atm_iv": 0.53599,
    "term_m1_m2": 1.48,
    "term_m1_m3": -2.17,
    "skew": -0.25,
    "iv_rank (HV)": 18.446896337953607,
    "iv_percentile (HV)": 37.99621928166352,
    "date": "2024-11-07"
  },
  {
    "atm_iv": 0.53299,
    "term_m1_m2": 1.54,
    "term_m1_m3": -3.08,
    "skew": -1.3,
    "iv_rank (HV)": 18.26308222151218,
    "iv_percentile (HV)": 37.523629489603024,
    "date": "2024-11-08"
  },
  {
    "atm_iv": 0.64718,
    "term_m1_m2": 4.59,
    "term_m1_m3": 2.46,
    "skew": -0.68,
    "iv_rank (HV)": 25.2596602069944,
    "iv_percentile (HV)": 60.49149338374291,
    "date": "2024-11-11"
  },
  {
    "atm_iv": 0.64781,
    "term_m1_m2": 5.53,
    "term_m1_m3": 2.98,
    "skew": -4.39,
    "iv_rank (HV)": 25.298261171447102,
    "iv_percentile (HV)": 60.49149338374291,
    "date": "2024-11-12"
  },
  {
    "atm_iv": 0.6108,
    "term_m1_m2": 3.61,
    "term_m1_m3": -0.01,
    "skew": -2.9,
    "iv_rank (HV)": 23.030607688281346,
    "iv_percentile (HV)": 51.701323251417776,
    "date": "2024-11-13"
  },
  {
    "atm_iv": 0.59156,
    "term_m1_m2": 2.57,
    "term_m1_m3": -1.06,
    "skew": -2.84,
    "iv_rank (HV)": 21.85174648817032,
    "iv_percentile (HV)": 48.39319470699433,
    "date": "2024-11-14"
  },
  {
    "atm_iv": 0.6118,
    "term_m1_m2": 3.34,
    "term_m1_m3": -0.68,
    "skew": -2.51,
    "iv_rank (HV)": 23.091879060428486,
    "iv_percentile (HV)": 51.98487712665406,
    "date": "2024-11-15"
  },
  {
    "atm_iv": 0.7001,
    "term_m1_m2": 6.65,
    "term_m1_m3": 3.83,
    "skew": -4.52,
    "iv_rank (HV)": 28.502141221021176,
    "iv_percentile (HV)": 69.37618147448015,
    "date": "2024-11-18"
  },
  {
    "atm_iv": 0.68931,
    "term_m1_m2": 4.91,
    "term_m1_m3": 2.03,
    "skew": -5.12,
    "iv_rank (HV)": 27.841023115553508,
    "iv_percentile (HV)": 67.58034026465029,
    "date": "2024-11-19"
  },
  {
    "atm_iv": 0.70965,
    "term_m1_m2": 4.42,
    "term_m1_m3": 0.79,
    "skew": -3.42,
    "iv_rank (HV)": 29.087282825026396,
    "iv_percentile (HV)": 73.06238185255198,
    "date": "2024-11-20"
  },
  {
    "atm_iv": 0.71529,
    "term_m1_m2": 5.72,
    "term_m1_m3": 1.82,
    "skew": -2.01,
    "iv_rank (HV)": 29.432853363936275,
    "iv_percentile (HV)": 73.81852551984878,
    "date": "2024-11-21"
  },
  {
    "atm_iv": 0.69538,
    "term_m1_m2": 3.55,
    "term_m1_m3": 0.35,
    "skew": -4.46,
    "iv_rank (HV)": 28.212940344486665,
    "iv_percentile (HV)": 68.62003780718337,
    "date": "2024-11-22"
  },
  {
    "atm_iv": 0.66622,
    "term_m1_m2": 3.08,
    "term_m1_m3": -1.12,
    "skew": -4.04,
    "iv_rank (HV)": 26.42626713267599,
    "iv_percentile (HV)": 63.61058601134215,
    "date": "2024-11-25"
  },
  {
    "atm_iv": 0.64628,
    "term_m1_m2": 2.96,
    "term_m1_m3": -0.81,
    "skew": -2.9,
    "iv_rank (HV)": 25.20451597206197,
    "iv_percentile (HV)": 60.113421550094515,
    "date": "2024-11-26"
  },
  {
    "atm_iv": 0.64034,
    "term_m1_m2": 2.53,
    "term_m1_m3": -1.76,
    "skew": -3.87,
    "iv_rank (HV)": 24.840564021507944,
    "iv_percentile (HV)": 58.60113421550095,
    "date": "2024-11-27"
  },
  {
    "atm_iv": 0.666,
    "term_m1_m2": 4.51,
    "term_m1_m3": -0.5,
    "skew": -4.79,
    "iv_rank (HV)": 26.412787430803625,
    "iv_percentile (HV)": 63.61058601134215,
    "date": "2024-11-29"
  },
  {
    "atm_iv": 0.70964,
    "term_m1_m2": 6.98,
    "term_m1_m3": 3.03,
    "skew": -6.46,
    "iv_rank (HV)": 29.08667011130492,
    "iv_percentile (HV)": 73.06238185255198,
    "date": "2024-12-02"
  },
  {
    "atm_iv": 0.6957,
    "term_m1_m2": 7.56,
    "term_m1_m3": 2.34,
    "skew": -7.0,
    "iv_rank (HV)": 28.232547183573747,
    "iv_percentile (HV)": 68.62003780718337,
    "date": "2024-12-03"
  },
  {
    "atm_iv": 0.64435,
    "term_m1_m2": 3.76,
    "term_m1_m3": -2.01,
    "skew": -6.14,
    "iv_rank (HV)": 25.086262223817986,
    "iv_percentile (HV)": 59.73534971644613,
    "date": "2024-12-04"
  },
  {
    "atm_iv": 0.65922,
    "term_m1_m2": 2.71,
    "term_m1_m3": -1.54,
    "skew": -8.5,
    "iv_rank (HV)": 25.99736752764599,
    "iv_percentile (HV)": 62.85444234404537,
    "date": "2024-12-05"
  },
  {
    "atm_iv": 0.61645,
    "term_m1_m2": -11.43,
    "term_m1_m3": -8.63,
    "skew": 4.57,
    "iv_rank (HV)": 23.376790940912702,
    "iv_percentile (HV)": 53.21361058601134,
    "date": "2025-01-02"
  },
  {
    "atm_iv": 0.57262,
    "term_m1_m2": -14.21,
    "term_m1_m3": -11.7,
    "skew": 2.17,
    "iv_rank (HV)": 20.691266699703444,
    "iv_percentile (HV)": 45.08506616257088,
    "date": "2025-01-03"
  },
  {
    "atm_iv": 0.73498,
    "term_m1_m2": 2.91,
    "term_m1_m3": 3.47,
    "skew": -0.68,
    "iv_rank (HV)": 30.639286681513507,
    "iv_percentile (HV)": 75.23629489603024,
    "date": "2025-01-06"
  },
  {
    "atm_iv": 0.74572,
    "term_m1_m2": 3.82,
    "term_m1_m3": 3.98,
    "skew": -0.01,
    "iv_rank (HV)": 31.297341218373827,
    "iv_percentile (HV)": 76.18147448015122,
    "date": "2025-01-07"
  },
  {
    "atm_iv": 0.7284,
    "term_m1_m2": 2.43,
    "term_m1_m3": 2.72,
    "skew": -0.23,
    "iv_rank (HV)": 30.236121052785318,
    "iv_percentile (HV)": 74.57466918714556,
    "date": "2025-01-08"
  },
  {
    "atm_iv": 0.74141,
    "term_m1_m2": 3.09,
    "term_m1_m3": 3.06,
    "skew": 0.2,
    "iv_rank (HV)": 31.033261604419643,
    "iv_percentile (HV)": 75.70888468809073,
    "date": "2025-01-10"
  },
  {
    "atm_iv": 0.75758,
    "term_m1_m2": 3.77,
    "term_m1_m3": 4.48,
    "skew": 0.35,
    "iv_rank (HV)": 32.02401969203894,
    "iv_percentile (HV)": 77.31568998109641,
    "date": "2025-01-13"
  },
  {
    "atm_iv": 0.76424,
    "term_m1_m2": 3.78,
    "term_m1_m3": 4.15,
    "skew": -0.15,
    "iv_rank (HV)": 32.43208703053891,
    "iv_percentile (HV)": 77.50472589792061,
    "date": "2025-01-14"
  },
  {
    "atm_iv": 0.74784,
    "term_m1_m2": 4.76,
    "term_m1_m3": 4.11,
    "skew": -0.11,
    "iv_rank (HV)": 31.427236527325764,
    "iv_percentile (HV)": 76.37051039697542,
    "date": "2025-01-15"
  },
  {
    "atm_iv": 0.73419,
    "term_m1_m2": 3.94,
    "term_m1_m3": 3.43,
    "skew": -1.32,
    "iv_rank (HV)": 30.59088229751727,
    "iv_percentile (HV)": 74.95274102079395,
    "date": "2025-01-16"
  },
  {
    "atm_iv": 0.74494,
    "term_m1_m2": 4.06,
    "term_m1_m3": 3.77,
    "skew": -2.8,
    "iv_rank (HV)": 31.249549548099054,
    "iv_percentile (HV)": 76.08695652173914,
    "date": "2025-01-17"
  },
  {
    "atm_iv": 0.75805,
    "term_m1_m2": 5.74,
    "term_m1_m3": 6.07,
    "skew": -3.79,
    "iv_rank (HV)": 32.0528172369481,
    "iv_percentile (HV)": 77.31568998109641,
    "date": "2025-01-21"
  },
  {
    "atm_iv": 0.73873,
    "term_m1_m2": 5.32,
    "term_m1_m3": 4.63,
    "skew": -2.42,
    "iv_rank (HV)": 30.869054327065303,
    "iv_percentile (HV)": 75.42533081285444,
    "date": "2025-01-22"
  },
  {
    "atm_iv": 0.73887,
    "term_m1_m2": 5.29,
    "term_m1_m3": 5.01,
    "skew": -1.41,
    "iv_rank (HV)": 30.877632319165897,
    "iv_percentile (HV)": 75.42533081285444,
    "date": "2025-01-23"
  },
  {
    "atm_iv": 0.72678,
    "term_m1_m2": 5.64,
    "term_m1_m3": 4.54,
    "skew": 3.36,
    "iv_rank (HV)": 30.13686142990694,
    "iv_percentile (HV)": 74.38563327032136,
    "date": "2025-01-24"
  },
  {
    "atm_iv": 0.77648,
    "term_m1_m2": 7.93,
    "term_m1_m3": 8.47,
    "skew": 0.69,
    "iv_rank (HV)": 33.18204862561993,
    "iv_percentile (HV)": 78.82797731568998,
    "date": "2025-01-27"
  },
  {
    "atm_iv": 0.77543,
    "term_m1_m2": 8.91,
    "term_m1_m3": 8.79,
    "skew": 0.03,
    "iv_rank (HV)": 33.11771368486542,
    "iv_percentile (HV)": 78.63894139886578,
    "date": "2025-01-28"
  },
  {
    "atm_iv": 0.80226,
    "term_m1_m2": 9.32,
    "term_m1_m3": 10.05,
    "skew": -0.55,
    "iv_rank (HV)": 34.76162459957327,
    "iv_percentile (HV)": 82.04158790170132,
    "date": "2025-01-29"
  },
  {
    "atm_iv": 0.81196,
    "term_m1_m2": 9.32,
    "term_m1_m3": 10.54,
    "skew": -0.26,
    "iv_rank (HV)": 35.35595690940055,
    "iv_percentile (HV)": 82.41965973534971,
    "date": "2025-01-30"
  },
  {
    "atm_iv": 0.79635,
    "term_m1_m2": 8.94,
    "term_m1_m3": 9.39,
    "skew": 0.56,
    "iv_rank (HV)": 34.399510790183655,
    "iv_percentile (HV)": 81.47448015122873,
    "date": "2025-01-31"
  },
  {
    "atm_iv": 0.84374,
    "term_m1_m2": 12.64,
    "term_m1_m3": 13.72,
    "skew": 0.94,
    "iv_rank (HV)": 37.30316111623675,
    "iv_percentile (HV)": 84.02646502835539,
    "date": "2025-02-03"
  },
  {
    "atm_iv": 0.88193,
    "term_m1_m2": 15.31,
    "term_m1_m3": 17.29,
    "skew": -0.74,
    "iv_rank (HV)": 39.64311481853612,
    "iv_percentile (HV)": 85.91682419659735,
    "date": "2025-02-04"
  },
  {
    "atm_iv": 0.87302,
    "term_m1_m2": 15.72,
    "term_m1_m3": 17.41,
    "skew": 0.19,
    "iv_rank (HV)": 39.09718689270508,
    "iv_percentile (HV)": 85.06616257088847,
    "date": "2025-02-05"
  },
  {
    "atm_iv": 0.87041,
    "term_m1_m2": 16.58,
    "term_m1_m3": 18.14,
    "skew": 0.53,
    "iv_rank (HV)": 38.93726861140103,
    "iv_percentile (HV)": 85.06616257088847,
    "date": "2025-02-06"
  },
  {
    "atm_iv": 0.89142,
    "term_m1_m2": 17.63,
    "term_m1_m3": 19.05,
    "skew": 0.55,
    "iv_rank (HV)": 40.224580140212495,
    "iv_percentile (HV)": 86.48393194706995,
    "date": "2025-02-07"
  },
  {
    "atm_iv": 0.73003,
    "term_m1_m2": 2.49,
    "term_m1_m3": 5.75,
    "skew": -0.49,
    "iv_rank (HV)": 30.33599338938516,
    "iv_percentile (HV)": 74.66918714555766,
    "date": "2025-02-10"
  },
  {
    "atm_iv": 0.72899,
    "term_m1_m2": 3.31,
    "term_m1_m3": 6.16,
    "skew": -0.85,
    "iv_rank (HV)": 30.272271162352133,
    "iv_percentile (HV)": 74.66918714555766,
    "date": "2025-02-11"
  },
  {
    "atm_iv": 0.74875,
    "term_m1_m2": 3.34,
    "term_m1_m3": 7.32,
    "skew": -2.46,
    "iv_rank (HV)": 31.482993475979665,
    "iv_percentile (HV)": 76.37051039697542,
    "date": "2025-02-12"
  },
  {
    "atm_iv": 0.59803,
    "term_m1_m2": -4.93,
    "term_m1_m3": -2.49,
    "skew": -3.21,
    "iv_rank (HV)": 22.248172265962335,
    "iv_percentile (HV)": 49.52741020793951,
    "date": "2025-02-13"
  },
  {
    "atm_iv": 0.57547,
    "term_m1_m2": -5.88,
    "term_m1_m3": -3.97,
    "skew": -2.29,
    "iv_rank (HV)": 20.8658901103228,
    "iv_percentile (HV)": 45.17958412098299,
    "date": "2025-02-14"
  },
  {
    "atm_iv": 0.59696,
    "term_m1_m2": -4.87,
    "term_m1_m3": -2.8,
    "skew": 0.23,
    "iv_rank (HV)": 22.182611897764893,
    "iv_percentile (HV)": 49.24385633270321,
    "date": "2025-02-18"
  },
  {
    "atm_iv": 0.59565,
    "term_m1_m2": -5.2,
    "term_m1_m3": -2.81,
    "skew": -2.07,
    "iv_rank (HV)": 22.102346400252138,
    "iv_percentile (HV)": 48.86578449905482,
    "date": "2025-02-19"
  },
  {
    "atm_iv": 0.59813,
    "term_m1_m2": -5.14,
    "term_m1_m3": -3.45,
    "skew": -0.18,
    "iv_rank (HV)": 22.254299403177054,
    "iv_percentile (HV)": 49.52741020793951,
    "date": "2025-02-20"
  },
  {
    "atm_iv": 0.63012,
    "term_m1_m2": -4.07,
    "term_m1_m3": -1.62,
    "skew": 4.0,
    "iv_rank (HV)": 24.21437059816414,
    "iv_percentile (HV)": 55.860113421550096,
    "date": "2025-02-21"
  },
  {
    "atm_iv": 0.64047,
    "term_m1_m2": -3.35,
    "term_m1_m3": -0.71,
    "skew": 3.09,
    "iv_rank (HV)": 24.84852929988707,
    "iv_percentile (HV)": 58.69565217391305,
    "date": "2025-02-24"
  },
  {
    "atm_iv": 0.70364,
    "term_m1_m2": 0.12,
    "term_m1_m3": 3.36,
    "skew": 6.02,
    "iv_rank (HV)": 28.71904187842207,
    "iv_percentile (HV)": 70.32136105860114,
    "date": "2025-02-25"
  },
  {
    "atm_iv": 0.70481,
    "term_m1_m2": -0.36,
    "term_m1_m3": 2.75,
    "skew": 4.04,
    "iv_rank (HV)": 28.79072938383423,
    "iv_percentile (HV)": 70.79395085066163,
    "date": "2025-02-26"
  },
  {
    "atm_iv": 0.7495,
    "term_m1_m2": 1.67,
    "term_m1_m3": 5.3,
    "skew": 7.82,
    "iv_rank (HV)": 31.528947005090025,
    "iv_percentile (HV)": 76.46502835538752,
    "date": "2025-02-27"
  },
  {
    "atm_iv": 0.71839,
    "term_m1_m2": -1.01,
    "term_m1_m3": 2.2,
    "skew": 6.61,
    "iv_rank (HV)": 29.62279461759242,
    "iv_percentile (HV)": 73.81852551984878,
    "date": "2025-02-28"
  },
  {
    "atm_iv": 0.84092,
    "term_m1_m2": 6.34,
    "term_m1_m3": 10.6,
    "skew": 7.39,
    "iv_rank (HV)": 37.130375846781796,
    "iv_percentile (HV)": 84.02646502835539,
    "date": "2025-03-03"
  },
  {
    "atm_iv": 0.86605,
    "term_m1_m2": 7.98,
    "term_m1_m3": 12.55,
    "skew": 4.78,
    "iv_rank (HV)": 38.6701254288395,
    "iv_percentile (HV)": 84.68809073724007,
    "date": "2025-03-04"
  },
  {
    "atm_iv": 0.83514,
    "term_m1_m2": 5.67,
    "term_m1_m3": 10.08,
    "skew": 5.82,
    "iv_rank (HV)": 36.776227315771315,
    "iv_percentile (HV)": 83.8374291115312,
    "date": "2025-03-05"
  },
  {
    "atm_iv": 0.89522,
    "term_m1_m2": 7.77,
    "term_m1_m3": 12.93,
    "skew": 7.95,
    "iv_rank (HV)": 40.45741135437165,
    "iv_percentile (HV)": 86.48393194706995,
    "date": "2025-03-06"
  },
  {
    "atm_iv": 0.88201,
    "term_m1_m2": 7.36,
    "term_m1_m3": 12.16,
    "skew": 6.18,
    "iv_rank (HV)": 39.648016528307885,
    "iv_percentile (HV)": 85.91682419659735,
    "date": "2025-03-07"
  },
  {
    "atm_iv": 0.80654,
    "term_m1_m2": 5.81,
    "term_m1_m3": 8.4,
    "skew": 5.75,
    "iv_rank (HV)": 35.023866072363035,
    "iv_percentile (HV)": 82.32514177693761,
    "date": "2025-03-31"
  },
  {
    "atm_iv": 0.81159,
    "term_m1_m2": 6.55,
    "term_m1_m3": 8.69,
    "skew": 4.6,
    "iv_rank (HV)": 35.33328650170611,
    "iv_percentile (HV)": 82.41965973534971,
    "date": "2025-04-01"
  },
  {
    "atm_iv": 0.79303,
    "term_m1_m2": 6.54,
    "term_m1_m3": 8.46,
    "skew": 5.09,
    "iv_rank (HV)": 34.19608983465514,
    "iv_percentile (HV)": 81.3623462630085,
    "date": "2025-04-02"
  },
  {
    "atm_iv": 0.87821,
    "term_m1_m2": 7.46,
    "term_m1_m3": 10.42,
    "skew": 7.75,
    "iv_rank (HV)": 39.415185314148744,
    "iv_percentile (HV)": 85.71428571428571,
    "date": "2025-04-03"
  },
  {
    "atm_iv": 1.02918,
    "term_m1_m2": 9.66,
    "term_m1_m3": 14.73,
    "skew": 15.65,
    "iv_rank (HV)": 48.66532436720286,
    "iv_percentile (HV)": 90.44465468306528,
    "date": "2025-04-04"
  },
  {
    "atm_iv": 1.0925,
    "term_m1_m2": 13.31,
    "term_m1_m3": 18.76,
    "skew": 14.32,
    "iv_rank (HV)": 52.54502765155993,
    "iv_percentile (HV)": 96.31031220435194,
    "date": "2025-04-07"
  },
  {
    "atm_iv": 1.17723,
    "term_m1_m2": 15.97,
    "term_m1_m3": 22.49,
    "skew": 20.2,
    "iv_rank (HV)": 57.736551013587324,
    "iv_percentile (HV)": 98.86471144749291,
    "date": "2025-04-08"
  },
  {
    "atm_iv": 0.88493,
    "term_m1_m2": 9.11,
    "term_m1_m3": 12.75,
    "skew": 11.81,
    "iv_rank (HV)": 39.82692893497754,
    "iv_percentile (HV)": 86.18732261116368,
    "date": "2025-04-09"
  },
  {
    "atm_iv": 1.00148,
    "term_m1_m2": 10.05,
    "term_m1_m3": 14.06,
    "skew": 18.36,
    "iv_rank (HV)": 46.96810735872701,
    "iv_percentile (HV)": 88.64711447492904,
    "date": "2025-04-10"
  },
  {
    "atm_iv": 0.92098,
    "term_m1_m2": 7.7,
    "term_m1_m3": 11.15,
    "skew": 12.45,
    "iv_rank (HV)": 42.03576190088204,
    "iv_percentile (HV)": 86.56575212866603,
    "date": "2025-04-11"
  },
  {
    "atm_iv": 0.87705,
    "term_m1_m2": 6.57,
    "term_m1_m3": 9.12,
    "skew": 8.83,
    "iv_rank (HV)": 39.34411052245806,
    "iv_percentile (HV)": 85.52507095553453,
    "date": "2025-04-14"
  },
  {
    "atm_iv": 0.83236,
    "term_m1_m2": 7.11,
    "term_m1_m3": 8.78,
    "skew": 9.7,
    "iv_rank (HV)": 36.60589290120227,
    "iv_percentile (HV)": 83.6329233680227,
    "date": "2025-04-15"
  },
  {
    "atm_iv": 0.89763,
    "term_m1_m2": 9.18,
    "term_m1_m3": 11.85,
    "skew": 11.14,
    "iv_rank (HV)": 40.60507536124626,
    "iv_percentile (HV)": 86.47114474929045,
    "date": "2025-04-16"
  },
  {
    "atm_iv": 0.85454,
    "term_m1_m2": 7.52,
    "term_m1_m3": 9.76,
    "skew": 9.22,
    "iv_rank (HV)": 37.964891935425875,
    "iv_percentile (HV)": 84.10596026490066,
    "date": "2025-04-17"
  },
  {
    "atm_iv": 0.92229,
    "term_m1_m2": 10.43,
    "term_m1_m3": 13.71,
    "skew": 10.21,
    "iv_rank (HV)": 42.11602739839479,
    "iv_percentile (HV)": 86.66035950804162,
    "date": "2025-04-21"
  },
  {
    "atm_iv": 0.93363,
    "term_m1_m2": 11.43,
    "term_m1_m3": 14.86,
    "skew": 7.32,
    "iv_rank (HV)": 42.81084475854339,
    "iv_percentile (HV)": 86.75496688741721,
    "date": "2025-04-22"
  },
  {
    "atm_iv": 0.90141,
    "term_m1_m2": 10.83,
    "term_m1_m3": 14.88,
    "skew": 6.83,
    "iv_rank (HV)": 40.83668114796246,
    "iv_percentile (HV)": 86.56575212866603,
    "date": "2025-04-23"
  },
  {
    "atm_iv": 0.91097,
    "term_m1_m2": 12.19,
    "term_m1_m3": 15.2,
    "skew": 7.17,
    "iv_rank (HV)": 41.422435465689134,
    "iv_percentile (HV)": 86.56575212866603,
    "date": "2025-04-24"
  },
  {
    "atm_iv": 0.88905,
    "term_m1_m2": 12.7,
    "term_m1_m3": 15.71,
    "skew": 6.5,
    "iv_rank (HV)": 40.079366988223775,
    "iv_percentile (HV)": 86.47114474929045,
    "date": "2025-04-25"
  },
  {
    "atm_iv": 0.94897,
    "term_m1_m2": 16.25,
    "term_m1_m3": 20.69,
    "skew": 7.15,
    "iv_rank (HV)": 43.75074760728055,
    "iv_percentile (HV)": 87.22800378429517,
    "date": "2025-04-28"
  },
  {
    "atm_iv": 0.94003,
    "term_m1_m2": 16.83,
    "term_m1_m3": 20.48,
    "skew": 5.88,
    "iv_rank (HV)": 43.2029815402851,
    "iv_percentile (HV)": 86.9441816461684,
    "date": "2025-04-29"
  },
  {
    "atm_iv": 0.924,
    "term_m1_m2": 15.87,
    "term_m1_m3": 19.31,
    "skew": 4.73,
    "iv_rank (HV)": 42.22080144476641,
    "iv_percentile (HV)": 86.66035950804162,
    "date": "2025-04-30"
  },
  {
    "atm_iv": 0.69945,
    "term_m1_m2": 2.99,
    "term_m1_m3": 3.74,
    "skew": 7.89,
    "iv_rank (HV)": 28.46231482912554,
    "iv_percentile (HV)": 69.15799432355723,
    "date": "2025-05-01"
  },
  {
    "atm_iv": 0.65174,
    "term_m1_m2": -0.85,
    "term_m1_m3": -0.33,
    "skew": 9.14,
    "iv_rank (HV)": 25.53905766398536,
    "iv_percentile (HV)": 60.9271523178808,
    "date": "2025-05-02"
  },
  {
    "atm_iv": 0.66871,
    "term_m1_m2": -0.35,
    "term_m1_m3": -4.43,
    "skew": 4.38,
    "iv_rank (HV)": 26.57883284932238,
    "iv_percentile (HV)": 64.1438032166509,
    "date": "2025-05-05"
  },
  {
    "atm_iv": 0.67416,
    "term_m1_m2": -0.2,
    "term_m1_m3": -3.4,
    "skew": 4.81,
    "iv_rank (HV)": 26.9127618275243,
    "iv_percentile (HV)": 65.1844843897824,
    "date": "2025-05-06"
  },
  {
    "atm_iv": 0.66201,
    "term_m1_m2": -0.34,
    "term_m1_m3": -3.7,
    "skew": 5.26,
    "iv_rank (HV)": 26.168314655936513,
    "iv_percentile (HV)": 63.0085146641438,
    "date": "2025-05-07"
  },
  {
    "atm_iv": 0.64079,
    "term_m1_m2": -0.32,
    "term_m1_m3": -5.06,
    "skew": 4.11,
    "iv_rank (HV)": 24.86813613897415,
    "iv_percentile (HV)": 58.84578997161779,
    "date": "2025-05-08"
  },
  {
    "atm_iv": 0.64542,
    "term_m1_m2": -0.64,
    "term_m1_m3": -4.94,
    "skew": 4.58,
    "iv_rank (HV)": 25.151822592015428,
    "iv_percentile (HV)": 60.07568590350048,
    "date": "2025-05-09"
  },
  {
    "atm_iv": 0.6009,
    "term_m1_m2": -0.65,
    "term_m1_m3": -5.68,
    "skew": 3.7,
    "iv_rank (HV)": 22.42402110402463,
    "iv_percentile (HV)": 49.85808893093661,
    "date": "2025-05-12"
  },
  {
    "atm_iv": 0.62974,
    "term_m1_m2": 0.69,
    "term_m1_m3": -3.72,
    "skew": 0.11,
    "iv_rank (HV)": 24.191087476748223,
    "iv_percentile (HV)": 55.81835383159886,
    "date": "2025-05-13"
  },
  {
    "atm_iv": 0.63122,
    "term_m1_m2": 1.13,
    "term_m1_m3": -3.01,
    "skew": 2.74,
    "iv_rank (HV)": 24.281769107526,
    "iv_percentile (HV)": 56.38599810785241,
    "date": "2025-05-14"
  },
  {
    "atm_iv": 0.62474,
    "term_m1_m2": 0.57,
    "term_m1_m3": -3.49,
    "skew": 2.52,
    "iv_rank (HV)": 23.884730616012508,
    "iv_percentile (HV)": 54.77767265846736,
    "date": "2025-05-15"
  },
  {
    "atm_iv": 0.61644,
    "term_m1_m2": -0.07,
    "term_m1_m3": -4.85,
    "skew": 3.88,
    "iv_rank (HV)": 23.37617822719123,
    "iv_percentile (HV)": 53.26395458845789,
    "date": "2025-05-16"
  },
  {
    "atm_iv": 0.63617,
    "term_m1_m2": 0.76,
    "term_m1_m3": -3.33,
    "skew": 2.4,
    "iv_rank (HV)": 24.58506239965436,
    "iv_percentile (HV)": 57.99432355723746,
    "date": "2025-05-19"
  },
  {
    "atm_iv": 0.63468,
    "term_m1_m2": 0.1,
    "term_m1_m3": -4.17,
    "skew": 3.62,
    "iv_rank (HV)": 24.493768055155115,
    "iv_percentile (HV)": 57.42667928098392,
    "date": "2025-05-20"
  },
  {
    "atm_iv": 0.67213,
    "term_m1_m2": 1.28,
    "term_m1_m3": -2.74,
    "skew": 3.87,
    "iv_rank (HV)": 26.788380942065597,
    "iv_percentile (HV)": 64.71144749290445,
    "date": "2025-05-21"
  },
  {
    "atm_iv": 0.66468,
    "term_m1_m2": 0.45,
    "term_m1_m3": -3.59,
    "skew": 4.18,
    "iv_rank (HV)": 26.331909219569393,
    "iv_percentile (HV)": 63.292336802270576,
    "date": "2025-05-22"
  },
  {
    "atm_iv": 0.67575,
    "term_m1_m2": 0.76,
    "term_m1_m3": -2.99,
    "skew": 4.0,
    "iv_rank (HV)": 27.01018330923826,
    "iv_percentile (HV)": 65.65752128666036,
    "date": "2025-05-23"
  },
  {
    "atm_iv": 0.66617,
    "term_m1_m2": 1.54,
    "term_m1_m3": -3.04,
    "skew": 3.2,
    "iv_rank (HV)": 26.423203564068636,
    "iv_percentile (HV)": 63.670766319772945,
    "date": "2025-05-27"
  },
  {
    "atm_iv": 0.65518,
    "term_m1_m2": 1.98,
    "term_m1_m3": -2.62,
    "skew": 2.97,
    "iv_rank (HV)": 25.749831184171533,
    "iv_percentile (HV)": 61.778618732261116,
    "date": "2025-05-28"
  },
  {
    "atm_iv": 0.64376,
    "term_m1_m2": 0.9,
    "term_m1_m3": -3.42,
    "skew": 3.17,
    "iv_rank (HV)": 25.05011211425117,
    "iv_percentile (HV)": 59.508041627246925,
    "date": "2025-05-29"
  },
  {
    "atm_iv": 0.63942,
    "term_m1_m2": 0.19,
    "term_m1_m3": -4.51,
    "skew": 3.11,
    "iv_rank (HV)": 24.784194359132563,
    "iv_percentile (HV)": 58.46736045411542,
    "date": "2025-05-30"
  },
  {
    "atm_iv": 0.68345,
    "term_m1_m2": 2.91,
    "term_m1_m3": -1.53,
    "skew": -1.6,
    "iv_rank (HV)": 27.481972874771255,
    "iv_percentile (HV)": 66.50898770104068,
    "date": "2025-06-02"
  },
  {
    "atm_iv": 0.69386,
    "term_m1_m2": 2.71,
    "term_m1_m3": -2.05,
    "skew": -3.96,
    "iv_rank (HV)": 28.119807858823016,
    "iv_percentile (HV)": 68.40113528855251,
    "date": "2025-06-03"
  },
  {
    "atm_iv": 0.69172,
    "term_m1_m2": 2.56,
    "term_m1_m3": -2.16,
    "skew": -1.91,
    "iv_rank (HV)": 27.988687122428125,
    "iv_percentile (HV)": 68.21192052980133,
    "date": "2025-06-04"
  },
  {
    "atm_iv": 0.75231,
    "term_m1_m2": 6.57,
    "term_m1_m3": 2.03,
    "skew": -2.01,
    "iv_rank (HV)": 31.7011195608235,
    "iv_percentile (HV)": 76.72658467360453,
    "date": "2025-06-05"
  },
  {
    "atm_iv": 0.76175,
    "term_m1_m2": 5.86,
    "term_m1_m3": 1.78,
    "skew": -2.75,
    "iv_rank (HV)": 32.279521313892516,
    "iv_percentile (HV)": 77.38883632923368,
    "date": "2025-06-06"
  },
  {
    "atm_iv": 0.62524,
    "term_m1_m2": -6.63,
    "term_m1_m3": -5.43,
    "skew": 2.08,
    "iv_rank (HV)": 23.91536630208609,
    "iv_percentile (HV)": 54.87228003784295,
    "date": "2025-06-09"
  },
  {
    "atm_iv": 0.63052,
    "term_m1_m2": -7.14,
    "term_m1_m3": -6.13,
    "skew": 2.31,
    "iv_rank (HV)": 24.238879147022995,
    "iv_percentile (HV)": 56.19678334910123,
    "date": "2025-06-10"
  },
  {
    "atm_iv": 0.62053,
    "term_m1_m2": -7.18,
    "term_m1_m3": -5.93,
    "skew": 2.26,
    "iv_rank (HV)": 23.626778139273043,
    "iv_percentile (HV)": 54.02081362346263,
    "date": "2025-06-11"
  },
  {
    "atm_iv": 0.60704,
    "term_m1_m2": -7.93,
    "term_m1_m3": -7.21,
    "skew": 2.08,
    "iv_rank (HV)": 22.800227329008088,
    "iv_percentile (HV)": 51.087984862819305,
    "date": "2025-06-12"
  },
  {
    "atm_iv": 0.62565,
    "term_m1_m2": -6.87,
    "term_m1_m3": -5.75,
    "skew": 5.55,
    "iv_rank (HV)": 23.940487564666412,
    "iv_percentile (HV)": 54.87228003784295,
    "date": "2025-06-13"
  },
  {
    "atm_iv": 0.60836,
    "term_m1_m2": -7.96,
    "term_m1_m3": -6.93,
    "skew": 3.81,
    "iv_rank (HV)": 22.88110554024232,
    "iv_percentile (HV)": 51.466414380321666,
    "date": "2025-06-16"
  },
  {
    "atm_iv": 0.61381,
    "term_m1_m2": -7.61,
    "term_m1_m3": -6.35,
    "skew": 5.37,
    "iv_rank (HV)": 23.21503451844425,
    "iv_percentile (HV)": 52.50709555345316,
    "date": "2025-06-17"
  },
  {
    "atm_iv": 0.61462,
    "term_m1_m2": -8.86,
    "term_m1_m3": -8.17,
    "skew": 5.0,
    "iv_rank (HV)": 23.264664329883438,
    "iv_percentile (HV)": 52.79091769157994,
    "date": "2025-06-18"
  },
  {
    "atm_iv": 0.60669,
    "term_m1_m2": -8.47,
    "term_m1_m3": -7.72,
    "skew": 6.52,
    "iv_rank (HV)": 22.77878234875659,
    "iv_percentile (HV)": 50.804162724692524,
    "date": "2025-06-20"
  },
  {
    "atm_iv": 0.58985,
    "term_m1_m2": -10.22,
    "term_m1_m3": -9.33,
    "skew": 5.02,
    "iv_rank (HV)": 21.74697244179871,
    "iv_percentile (HV)": 47.776726584673604,
    "date": "2025-06-23"
  },
  {
    "atm_iv": 0.54211,
    "term_m1_m2": -13.82,
    "term_m1_m3": -11.3,
    "skew": 1.96,
    "iv_rank (HV)": 18.82187713549412,
    "iv_percentile (HV)": 39.35666982024598,
    "date": "2025-06-24"
  },
  {
    "atm_iv": 0.58331,
    "term_m1_m2": -11.1,
    "term_m1_m3": -9.39,
    "skew": 3.39,
    "iv_rank (HV)": 21.3462576679564,
    "iv_percentile (HV)": 46.830652790917696,
    "date": "2025-06-25"
  },
  {
    "atm_iv": 0.57591,
    "term_m1_m2": -11.61,
    "term_m1_m3": -9.52,
    "skew": 4.07,
    "iv_rank (HV)": 20.892849514067542,
    "iv_percentile (HV)": 45.31693472090823,
    "date": "2025-06-26"
  },
  {
    "atm_iv": 0.5752,
    "term_m1_m2": -10.83,
    "term_m1_m3": -9.22,
    "skew": 3.76,
    "iv_rank (HV)": 20.84934683984307,
    "iv_percentile (HV)": 45.22232734153264,
    "date": "2025-06-27"
  },
  {
    "atm_iv": 0.71789,
    "term_m1_m2": -5.56,
    "term_m1_m3": -0.91,
    "skew": -6.81,
    "iv_rank (HV)": 29.592158931518846,
    "iv_percentile (HV)": 73.8883632923368,
    "date": "2025-06-30"
  },
  {
    "atm_iv": 0.7311,
    "term_m1_m2": -7.16,
    "term_m1_m3": -1.51,
    "skew": -3.96,
    "iv_rank (HV)": 30.4015537575826,
    "iv_percentile (HV)": 74.73982970671712,
    "date": "2025-07-01"
  },
  {
    "atm_iv": 0.7632,
    "term_m1_m2": -4.01,
    "term_m1_m3": -0.08,
    "skew": -5.83,
    "iv_rank (HV)": 32.36836480350587,
    "iv_percentile (HV)": 77.57805108798486,
    "date": "2025-07-02"
  },
  {
    "atm_iv": 0.67836,
    "term_m1_m2": -8.96,
    "term_m1_m3": -4.81,
    "skew": -2.74,
    "iv_rank (HV)": 27.170101590542302,
    "iv_percentile (HV)": 65.84673604541155,
    "date": "2025-07-03"
  },
  {
    "atm_iv": 0.7576,
    "term_m1_m2": 4.66,
    "term_m1_m3": 5.48,
    "skew": 0.04,
    "iv_rank (HV)": 32.02524511948188,
    "iv_percentile (HV)": 77.38883632923368,
    "date": "2025-07-07"
  },
  {
    "atm_iv": 0.73686,
    "term_m1_m2": 3.58,
    "term_m1_m3": 5.1,
    "skew": -0.13,
    "iv_rank (HV)": 30.75447686115014,
    "iv_percentile (HV)": 75.40208136234627,
    "date": "2025-07-08"
  },
  {
    "atm_iv": 0.7252,
    "term_m1_m2": 3.75,
    "term_m1_m3": 5.52,
    "skew": -0.13,
    "iv_rank (HV)": 30.04005266191446,
    "iv_percentile (HV)": 74.36140018921475,
    "date": "2025-07-09"
  },
  {
    "atm_iv": 0.72342,
    "term_m1_m2": 3.43,
    "term_m1_m3": 5.32,
    "skew": -1.4,
    "iv_rank (HV)": 29.930989619492543,
    "iv_percentile (HV)": 74.26679280983916,
    "date": "2025-07-10"
  },
  {
    "atm_iv": 0.72011,
    "term_m1_m2": 4.38,
    "term_m1_m3": 6.04,
    "skew": -0.21,
    "iv_rank (HV)": 29.7281813776855,
    "iv_percentile (HV)": 74.07757805108798,
    "date": "2025-07-11"
  },
  {
    "atm_iv": 0.73026,
    "term_m1_m2": 4.89,
    "term_m1_m3": 6.64,
    "skew": -1.22,
    "iv_rank (HV)": 30.350085804979,
    "iv_percentile (HV)": 74.73982970671712,
    "date": "2025-07-14"
  },
  {
    "atm_iv": 0.7307,
    "term_m1_m2": 5.19,
    "term_m1_m3": 6.85,
    "skew": -0.5,
    "iv_rank (HV)": 30.377045208723747,
    "iv_percentile (HV)": 74.73982970671712,
    "date": "2025-07-15"
  },
  {
    "atm_iv": 0.72889,
    "term_m1_m2": 4.97,
    "term_m1_m3": 5.9,
    "skew": -1.08,
    "iv_rank (HV)": 30.26614402513742,
    "iv_percentile (HV)": 74.73982970671712,
    "date": "2025-07-16"
  },
  {
    "atm_iv": 0.72554,
    "term_m1_m2": 4.67,
    "term_m1_m3": 6.44,
    "skew": -0.23,
    "iv_rank (HV)": 30.060884928444487,
    "iv_percentile (HV)": 74.36140018921475,
    "date": "2025-07-17"
  },
  {
    "atm_iv": 0.75629,
    "term_m1_m2": 6.53,
    "term_m1_m3": 8.16,
    "skew": -2.06,
    "iv_rank (HV)": 31.94497962196913,
    "iv_percentile (HV)": 77.01040681173131,
    "date": "2025-07-18"
  },
  {
    "atm_iv": 0.74055,
    "term_m1_m2": 6.4,
    "term_m1_m3": 8.06,
    "skew": 0.25,
    "iv_rank (HV)": 30.9805682243731,
    "iv_percentile (HV)": 75.68590350047305,
    "date": "2025-07-21"
  },
  {
    "atm_iv": 0.72342,
    "term_m1_m2": 6.24,
    "term_m1_m3": 7.05,
    "skew": 2.1,
    "iv_rank (HV)": 29.930989619492543,
    "iv_percentile (HV)": 74.26679280983916,
    "date": "2025-07-22"
  },
  {
    "atm_iv": 0.70906,
    "term_m1_m2": 5.86,
    "term_m1_m3": 6.77,
    "skew": 1.45,
    "iv_rank (HV)": 29.05113271545958,
    "iv_percentile (HV)": 72.94228949858089,
    "date": "2025-07-23"
  },
  {
    "atm_iv": 0.69068,
    "term_m1_m2": 5.75,
    "term_m1_m3": 6.15,
    "skew": 1.42,
    "iv_rank (HV)": 27.9249648953951,
    "iv_percentile (HV)": 68.11731315042573,
    "date": "2025-07-24"
  },
  {
    "atm_iv": 0.67244,
    "term_m1_m2": 4.96,
    "term_m1_m3": 5.59,
    "skew": 1.06,
    "iv_rank (HV)": 26.807375067431217,
    "iv_percentile (HV)": 64.80605487228004,
    "date": "2025-07-25"
  },
  {
    "atm_iv": 0.71505,
    "term_m1_m2": 8.1,
    "term_m1_m3": 8.86,
    "skew": -1.24,
    "iv_rank (HV)": 29.41814823462096,
    "iv_percentile (HV)": 73.8883632923368,
    "date": "2025-07-28"
  },
  {
    "atm_iv": 0.77186,
    "term_m1_m2": 10.98,
    "term_m1_m3": 13.34,
    "skew": 1.0,
    "iv_rank (HV)": 32.89897488630013,
    "iv_percentile (HV)": 78.240302743614,
    "date": "2025-07-29"
  },
  {
    "atm_iv": 0.74656,
    "term_m1_m2": 10.45,
    "term_m1_m3": 11.57,
    "skew": 2.38,
    "iv_rank (HV)": 31.348809170977425,
    "iv_percentile (HV)": 76.34815515610217,
    "date": "2025-07-30"
  },
  {
    "atm_iv": 0.60468,
    "term_m1_m2": 0.71,
    "term_m1_m3": 0.47,
    "skew": 0.26,
    "iv_rank (HV)": 22.65562689074083,
    "iv_percentile (HV)": 50.52034058656575,
    "date": "2025-07-31"
  },
  {
    "atm_iv": 0.66601,
    "term_m1_m2": 2.09,
    "term_m1_m3": 3.1,
    "skew": 7.18,
    "iv_rank (HV)": 26.41340014452509,
    "iv_percentile (HV)": 63.670766319772945,
    "date": "2025-08-01"
  },
  {
    "atm_iv": 0.62399,
    "term_m1_m2": -0.03,
    "term_m1_m3": -3.71,
    "skew": 4.07,
    "iv_rank (HV)": 23.83877708690216,
    "iv_percentile (HV)": 54.68306527909177,
    "date": "2025-08-04"
  },
  {
    "atm_iv": 0.62952,
    "term_m1_m2": 0.0,
    "term_m1_m3": -2.55,
    "skew": 4.24,
    "iv_rank (HV)": 24.177607774875856,
    "iv_percentile (HV)": 55.723746452223274,
    "date": "2025-08-05"
  },
  {
    "atm_iv": 0.62692,
    "term_m1_m2": -0.09,
    "term_m1_m3": -2.89,
    "skew": 3.79,
    "iv_rank (HV)": 24.01830220729328,
    "iv_percentile (HV)": 55.4399243140965,
    "date": "2025-08-06"
  },
  {
    "atm_iv": 0.62457,
    "term_m1_m2": 0.16,
    "term_m1_m3": -3.89,
    "skew": 4.02,
    "iv_rank (HV)": 23.874314482747497,
    "iv_percentile (HV)": 54.77767265846736,
    "date": "2025-08-07"
  },
  {
    "atm_iv": 0.60901,
    "term_m1_m2": -0.84,
    "term_m1_m3": -5.14,
    "skew": 2.61,
    "iv_rank (HV)": 22.92093193213796,
    "iv_percentile (HV)": 51.466414380321666,
    "date": "2025-08-08"
  },
  {
    "atm_iv": 0.616,
    "term_m1_m2": -0.83,
    "term_m1_m3": -4.74,
    "skew": 5.87,
    "iv_rank (HV)": 23.349218823446485,
    "iv_percentile (HV)": 53.074739829706715,
    "date": "2025-08-11"
  },
  {
    "atm_iv": 0.59911,
    "term_m1_m2": -1.0,
    "term_m1_m3": -4.82,
    "skew": 4.52,
    "iv_rank (HV)": 22.31434534788125,
    "iv_percentile (HV)": 49.57426679280984,
    "date": "2025-08-12"
  },
  {
    "atm_iv": 0.62249,
    "term_m1_m2": -0.02,
    "term_m1_m3": -2.8,
    "skew": 4.95,
    "iv_rank (HV)": 23.746870028681442,
    "iv_percentile (HV)": 54.39924314096499,
    "date": "2025-08-13"
  },
  {
    "atm_iv": 0.61242,
    "term_m1_m2": 0.28,
    "term_m1_m3": -3.32,
    "skew": 3.22,
    "iv_rank (HV)": 23.129867311159714,
    "iv_percentile (HV)": 52.1286660359508,
    "date": "2025-08-14"
  },
  {
    "atm_iv": 0.60316,
    "term_m1_m2": 0.1,
    "term_m1_m3": -3.95,
    "skew": 4.62,
    "iv_rank (HV)": 22.562494405077178,
    "iv_percentile (HV)": 50.14191106906338,
    "date": "2025-08-15"
  },
  {
    "atm_iv": 0.59907,
    "term_m1_m2": 0.06,
    "term_m1_m3": -4.71,
    "skew": 3.28,
    "iv_rank (HV)": 22.311894492995364,
    "iv_percentile (HV)": 49.57426679280984,
    "date": "2025-08-18"
  },
  {
    "atm_iv": 0.65709,
    "term_m1_m2": 1.59,
    "term_m1_m3": -1.76,
    "skew": 7.36,
    "iv_rank (HV)": 25.866859504972574,
    "iv_percentile (HV)": 62.251655629139066,
    "date": "2025-08-19"
  },
  {
    "atm_iv": 0.65947,
    "term_m1_m2": 1.04,
    "term_m1_m3": -1.3,
    "skew": 7.17,
    "iv_rank (HV)": 26.01268537068278,
    "iv_percentile (HV)": 62.913907284768214,
    "date": "2025-08-20"
  },
  {
    "atm_iv": 0.65181,
    "term_m1_m2": 1.16,
    "term_m1_m3": -2.13,
    "skew": 7.65,
    "iv_rank (HV)": 25.543346660035667,
    "iv_percentile (HV)": 60.9271523178808,
    "date": "2025-08-21"
  },
  {
    "atm_iv": 0.62998,
    "term_m1_m2": 0.76,
    "term_m1_m3": -2.99,
    "skew": 4.35,
    "iv_rank (HV)": 24.205792606063536,
    "iv_percentile (HV)": 55.91296121097445,
    "date": "2025-08-22"
  },
  {
    "atm_iv": 0.65878,
    "term_m1_m2": 2.15,
    "term_m1_m3": -1.32,
    "skew": 6.1,
    "iv_rank (HV)": 25.97040812390125,
    "iv_percentile (HV)": 62.72469252601704,
    "date": "2025-08-25"
  },
  {
    "atm_iv": 0.63864,
    "term_m1_m2": 1.42,
    "term_m1_m3": -1.79,
    "skew": 7.4,
    "iv_rank (HV)": 24.73640268885779,
    "iv_percentile (HV)": 58.46736045411542,
    "date": "2025-08-26"
  },
  {
    "atm_iv": 0.65281,
    "term_m1_m2": 1.5,
    "term_m1_m3": -1.5,
    "skew": 4.3,
    "iv_rank (HV)": 25.604618032182813,
    "iv_percentile (HV)": 61.30558183538316,
    "date": "2025-08-27"
  },
  {
    "atm_iv": 0.61163,
    "term_m1_m2": 0.94,
    "term_m1_m3": -2.59,
    "skew": 2.87,
    "iv_rank (HV)": 23.081462927163475,
    "iv_percentile (HV)": 52.03405865657521,
    "date": "2025-08-28"
  },
  {
    "atm_iv": 0.60163,
    "term_m1_m2": 1.1,
    "term_m1_m3": -3.59,
    "skew": 4.07,
    "iv_rank (HV)": 22.46874920569205,
    "iv_percentile (HV)": 49.952696310312206,
    "date": "2025-08-29"
  },
  {
    "atm_iv": 0.64764,
    "term_m1_m2": 3.69,
    "term_m1_m3": -0.08,
    "skew": 8.52,
    "iv_rank (HV)": 25.287845038182077,
    "iv_percentile (HV)": 60.54872280037843,
    "date": "2025-09-02"
  },
  {
    "atm_iv": 0.62828,
    "term_m1_m2": 3.04,
    "term_m1_m3": -1.17,
    "skew": 7.36,
    "iv_rank (HV)": 24.101631273413393,
    "iv_percentile (HV)": 55.53453169347209,
    "date": "2025-09-03"
  },
  {
    "atm_iv": 0.61836,
    "term_m1_m2": 2.7,
    "term_m1_m3": -1.56,
    "skew": 5.06,
    "iv_rank (HV)": 23.493819261713746,
    "iv_percentile (HV)": 53.92620624408704,
    "date": "2025-09-04"
  },
  {
    "atm_iv": 0.66993,
    "term_m1_m2": 4.89,
    "term_m1_m3": 0.95,
    "skew": 4.06,
    "iv_rank (HV)": 26.653583923341895,
    "iv_percentile (HV)": 64.42762535477767,
    "date": "2025-09-05"
  },
  {
    "atm_iv": 0.58953,
    "term_m1_m2": -5.03,
    "term_m1_m3": -3.89,
    "skew": 4.16,
    "iv_rank (HV)": 21.727365602711625,
    "iv_percentile (HV)": 47.776726584673604,
    "date": "2025-09-08"
  },
  {
    "atm_iv": 0.59221,
    "term_m1_m2": -4.85,
    "term_m1_m3": -3.91,
    "skew": 3.81,
    "iv_rank (HV)": 21.891572880065972,
    "iv_percentile (HV)": 48.533585619678334,
    "date": "2025-09-09"
  },
  {
    "atm_iv": 0.5949,
    "term_m1_m2": -5.33,
    "term_m1_m3": -4.04,
    "skew": 5.06,
    "iv_rank (HV)": 22.056392871141778,
    "iv_percentile (HV)": 48.912015137180695,
    "date": "2025-09-10"
  },
  {
    "atm_iv": 0.56938,
    "term_m1_m2": -5.15,
    "term_m1_m3": -4.43,
    "skew": 4.42,
    "iv_rank (HV)": 20.492747453946702,
    "iv_percentile (HV)": 43.99243140964995,
    "date": "2025-09-11"
  },
  {
    "atm_iv": 0.56877,
    "term_m1_m2": -5.25,
    "term_m1_m3": -4.02,
    "skew": 2.81,
    "iv_rank (HV)": 20.455371916936944,
    "iv_percentile (HV)": 43.80321665089877,
    "date": "2025-09-12"
  },
  {
    "atm_iv": 0.5905,
    "term_m1_m2": -4.26,
    "term_m1_m3": -2.93,
    "skew": 4.38,
    "iv_rank (HV)": 21.786798833694352,
    "iv_percentile (HV)": 48.24976348155156,
    "date": "2025-09-15"
  },
  {
    "atm_iv": 0.59344,
    "term_m1_m2": -4.26,
    "term_m1_m3": -3.08,
    "skew": 3.71,
    "iv_rank (HV)": 21.966936667806948,
    "iv_percentile (HV)": 48.72280037842952,
    "date": "2025-09-16"
  },
  {
    "atm_iv": 0.5764,
    "term_m1_m2": -5.38,
    "term_m1_m3": -4.55,
    "skew": 3.95,
    "iv_rank (HV)": 20.922872486419646,
    "iv_percentile (HV)": 45.31693472090823,
    "date": "2025-09-17"
  },
  {
    "atm_iv": 0.57044,
    "term_m1_m2": -6.02,
    "term_m1_m3": -5.0,
    "skew": 0.95,
    "iv_rank (HV)": 20.55769510842267,
    "iv_percentile (HV)": 44.370860927152314,
    "date": "2025-09-18"
  },
  {
    "atm_iv": 0.56001,
    "term_m1_m2": -6.19,
    "term_m1_m3": -5.18,
    "skew": 3.89,
    "iv_rank (HV)": 19.91863469692797,
    "iv_percentile (HV)": 42.66792809839167,
    "date": "2025-09-19"
  },
  {
    "atm_iv": 0.56757,
    "term_m1_m2": -6.32,
    "term_m1_m3": -5.22,
    "skew": 2.15,
    "iv_rank (HV)": 20.381846270360377,
    "iv_percentile (HV)": 43.33017975402081,
    "date": "2025-09-22"
  },
  {
    "atm_iv": 0.57948,
    "term_m1_m2": -6.65,
    "term_m1_m3": -5.57,
    "skew": 4.4,
    "iv_rank (HV)": 21.111588312632836,
    "iv_percentile (HV)": 46.16840113528855,
    "date": "2025-09-23"
  },
  {
    "atm_iv": 0.57836,
    "term_m1_m2": -7.36,
    "term_m1_m3": -6.47,
    "skew": 5.5,
    "iv_rank (HV)": 21.042964375828042,
    "iv_percentile (HV)": 45.789971617786186,
    "date": "2025-09-24"
  },
  {
    "atm_iv": 0.58512,
    "term_m1_m2": -7.43,
    "term_m1_m3": -6.28,
    "skew": 6.53,
    "iv_rank (HV)": 21.457158851542726,
    "iv_percentile (HV)": 47.11447492904446,
    "date": "2025-09-25"
  },
  {
    "atm_iv": 0.54956,
    "term_m1_m2": -8.72,
    "term_m1_m3": -8.01,
    "skew": 6.18,
    "iv_rank (HV)": 19.278348857990334,
    "iv_percentile (HV)": 41.05960264900662,
    "date": "2025-09-26"
  },
  {
    "atm_iv": 0.62078,
    "term_m1_m2": -6.04,
    "term_m1_m3": -4.97,
    "skew": 1.97,
    "iv_rank (HV)": 23.642095982309833,
    "iv_percentile (HV)": 54.210028382213814,
    "date": "2025-09-29"
  },
  {
    "atm_iv": 0.63473,
    "term_m1_m2": -6.22,
    "term_m1_m3": -5.03,
    "skew": 4.85,
    "iv_rank (HV)": 24.496831623762468,
    "iv_percentile (HV)": 57.42667928098392,
    "date": "2025-09-30"
  },
  {
    "atm_iv": 0.58698,
    "term_m1_m2": -8.2,
    "term_m1_m3": -7.43,
    "skew": 6.14,
    "iv_rank (HV)": 21.57112360373641,
    "iv_percentile (HV)": 47.30368968779565,
    "date": "2025-10-01"
  },
  {
    "atm_iv": 0.60382,
    "term_m1_m2": -8.95,
    "term_m1_m3": -8.08,
    "skew": 5.43,
    "iv_rank (HV)": 22.602933510694296,
    "iv_percentile (HV)": 50.331125827814574,
    "date": "2025-10-02"
  },
  {
    "atm_iv": 0.59621,
    "term_m1_m2": -8.48,
    "term_m1_m3": -7.6,
    "skew": 6.72,
    "iv_rank (HV)": 22.136658368654537,
    "iv_percentile (HV)": 49.00662251655629,
    "date": "2025-10-03"
  },
  {
    "atm_iv": 0.69585,
    "term_m1_m2": 1.55,
    "term_m1_m3": 2.86,
    "skew": 2.86,
    "iv_rank (HV)": 28.241737889395818,
    "iv_percentile (HV)": 68.68495742667929,
    "date": "2025-10-06"
  },
  {
    "atm_iv": 0.69879,
    "term_m1_m2": 1.72,
    "term_m1_m3": 3.37,
    "skew": 3.78,
    "iv_rank (HV)": 28.42187572350843,
    "iv_percentile (HV)": 69.06338694418164,
    "date": "2025-10-07"
  },
  {
    "atm_iv": 0.69346,
    "term_m1_m2": 1.31,
    "term_m1_m3": 2.58,
    "skew": 2.72,
    "iv_rank (HV)": 28.095299309964155,
    "iv_percentile (HV)": 68.30652790917692,
    "date": "2025-10-08"
  },
  {
    "atm_iv": 0.68917,
    "term_m1_m2": 0.71,
    "term_m1_m3": 1.88,
    "skew": 2.89,
    "iv_rank (HV)": 27.832445123452914,
    "iv_percentile (HV)": 67.64427625354777,
    "date": "2025-10-09"
  },
  {
    "atm_iv": 0.7404,
    "term_m1_m2": 1.85,
    "term_m1_m3": 3.54,
    "skew": 7.28,
    "iv_rank (HV)": 30.971377518551023,
    "iv_percentile (HV)": 75.68590350047305,
    "date": "2025-10-10"
  },
  {
    "atm_iv": 0.72263,
    "term_m1_m2": 2.42,
    "term_m1_m3": 4.14,
    "skew": 4.7,
    "iv_rank (HV)": 29.882585235496308,
    "iv_percentile (HV)": 74.26679280983916,
    "date": "2025-10-13"
  },
  {
    "atm_iv": 0.73707,
    "term_m1_m2": 3.24,
    "term_m1_m3": 5.1,
    "skew": 5.67,
    "iv_rank (HV)": 30.76734384930104,
    "iv_percentile (HV)": 75.40208136234627,
    "date": "2025-10-14"
  },
  {
    "atm_iv": 0.73666,
    "term_m1_m2": 3.45,
    "term_m1_m3": 5.2,
    "skew": 4.91,
    "iv_rank (HV)": 30.742222586720715,
    "iv_percentile (HV)": 75.40208136234627,
    "date": "2025-10-15"
  },
  {
    "atm_iv": 0.77432,
    "term_m1_m2": 4.26,
    "term_m1_m3": 6.55,
    "skew": 7.68,
    "iv_rank (HV)": 33.049702461782104,
    "iv_percentile (HV)": 78.42951750236519,
    "date": "2025-10-16"
  },
  {
    "atm_iv": 0.72918,
    "term_m1_m2": 3.36,
    "term_m1_m3": 5.34,
    "skew": 7.64,
    "iv_rank (HV)": 30.28391272306009,
    "iv_percentile (HV)": 74.73982970671712,
    "date": "2025-10-17"
  },
  {
    "atm_iv": 0.72926,
    "term_m1_m2": 3.77,
    "term_m1_m3": 5.74,
    "skew": 6.79,
    "iv_rank (HV)": 30.288814432831863,
    "iv_percentile (HV)": 74.73982970671712,
    "date": "2025-10-20"
  },
  {
    "atm_iv": 0.72156,
    "term_m1_m2": 3.63,
    "term_m1_m3": 5.27,
    "skew": 5.77,
    "iv_rank (HV)": 29.81702486729886,
    "iv_percentile (HV)": 74.17218543046357,
    "date": "2025-10-21"
  },
  {
    "atm_iv": 0.75519,
    "term_m1_m2": 4.8,
    "term_m1_m3": 6.94,
    "skew": 6.53,
    "iv_rank (HV)": 31.877581112607267,
    "iv_percentile (HV)": 76.72658467360453,
    "date": "2025-10-22"
  },
  {
    "atm_iv": 0.72679,
    "term_m1_m2": 4.4,
    "term_m1_m3": 5.86,
    "skew": 5.19,
    "iv_rank (HV)": 30.137474143628417,
    "iv_percentile (HV)": 74.45600756859035,
    "date": "2025-10-23"
  },
  {
    "atm_iv": 0.72311,
    "term_m1_m2": 4.24,
    "term_m1_m3": 5.79,
    "skew": 4.93,
    "iv_rank (HV)": 29.911995494126938,
    "iv_percentile (HV)": 74.26679280983916,
    "date": "2025-10-24"
  },
  {
    "atm_iv": 0.73071,
    "term_m1_m2": 4.16,
    "term_m1_m3": 6.22,
    "skew": 3.91,
    "iv_rank (HV)": 30.377657922445213,
    "iv_percentile (HV)": 74.73982970671712,
    "date": "2025-10-27"
  },
  {
    "atm_iv": 0.73827,
    "term_m1_m2": 4.59,
    "term_m1_m3": 6.31,
    "skew": 4.58,
    "iv_rank (HV)": 30.84086949587761,
    "iv_percentile (HV)": 75.40208136234627,
    "date": "2025-10-28"
  },
  {
    "atm_iv": 0.77537,
    "term_m1_m2": 6.9,
    "term_m1_m3": 9.24,
    "skew": 3.25,
    "iv_rank (HV)": 33.1140374025366,
    "iv_percentile (HV)": 78.71333964049197,
    "date": "2025-10-29"
  },
  {
    "atm_iv": 0.75262,
    "term_m1_m2": 5.26,
    "term_m1_m3": 7.45,
    "skew": 3.87,
    "iv_rank (HV)": 31.720113686189112,
    "iv_percentile (HV)": 76.72658467360453,
    "date": "2025-10-30"
  },
  {
    "date": "2025-10-31",
    "atm_iv": 0.7663,
    "iv_rank (HV)": 32.55830605716202,
    "iv_percentile (HV)": 77.57805108798486,
    "term_m1_m2": 6.22,
    "term_m1_m3": 7.75,
    "skew": 4.71
  },
  {
    "date": "2025-11-03",
    "atm_iv": 0.78686,
    "iv_rank (HV)": 33.81804546850727,
    "iv_percentile (HV)": 80.22705771050141,
    "term_m1_m2": 7.38,
    "term_m1_m3": 9.64,
    "skew": 3.44
  },
  {
    "date": "2025-11-04",
    "atm_iv": 0.82957,
    "iv_rank (HV)": 36.43494577291174,
    "iv_percentile (HV)": 83.53831598864711,
    "term_m1_m2": 10.42,
    "term_m1_m3": 13.15,
    "skew": 4.27
  },
  {
    "date": "2025-11-05",
    "atm_iv": 0.74357,
    "iv_rank (HV)": 31.16560776825747,
    "iv_percentile (HV)": 76.0643330179754,
    "term_m1_m2": 6.21,
    "term_m1_m3": 7.34,
    "skew": 4.75
  },
  {
    "date": "2025-11-06",
    "atm_iv": 0.70017,
    "iv_rank (HV)": 28.506430217071475,
    "iv_percentile (HV)": 69.44181646168401,
    "term_m1_m2": 1.26,
    "term_m1_m3": 1.93,
    "skew": 4.31
  },
  {
    "date": "2025-11-07",
    "atm_iv": 0.67849,
    "iv_rank (HV)": 27.17806686892143,
    "iv_percentile (HV)": 65.94134342478714,
    "term_m1_m2": -0.67,
    "term_m1_m3": -0.42,
    "skew": 2.84
  },
  {
    "date": "2025-11-10",
    "atm_iv": 0.66854,
    "iv_rank (HV)": 26.568416716057357,
    "iv_percentile (HV)": 64.1438032166509,
    "term_m1_m2": 0.81,
    "term_m1_m3": -2.22,
    "skew": 4.49
  },
  {
    "date": "2025-11-11",
    "atm_iv": 0.65804,
    "iv_rank (HV)": 25.925067308512368,
    "iv_percentile (HV)": 62.535477767265846,
    "term_m1_m2": 0.48,
    "term_m1_m3": -2.55,
    "skew": 3.67
  },
  {
    "date": "2025-11-12",
    "atm_iv": 0.65115,
    "iv_rank (HV)": 25.502907554418545,
    "iv_percentile (HV)": 60.9271523178808,
    "term_m1_m2": 1.07,
    "term_m1_m3": -2.43,
    "skew": 3.75
  },
  {
    "date": "2025-11-13",
    "atm_iv": 0.70869,
    "iv_rank (HV)": 29.028462307765135,
    "iv_percentile (HV)": 72.84768211920529,
    "term_m1_m2": 2.06,
    "term_m1_m3": -0.88,
    "skew": 5.44
  },
  {
    "date": "2025-11-14",
    "atm_iv": 0.67516,
    "iv_rank (HV)": 26.97403319967144,
    "iv_percentile (HV)": 65.56291390728477,
    "term_m1_m2": 1.03,
    "term_m1_m3": -2.02,
    "skew": 5.8
  },
  {
    "date": "2025-11-17",
    "atm_iv": 0.72226,
    "iv_rank (HV)": 29.85991482780186,
    "iv_percentile (HV)": 74.26679280983916,
    "term_m1_m2": 2.55,
    "term_m1_m3": 0.93,
    "skew": 7.55
  },
  {
    "date": "2025-11-18",
    "atm_iv": 0.72778,
    "iv_rank (HV)": 30.198132802054083,
    "iv_percentile (HV)": 74.55061494796594,
    "term_m1_m2": 2.57,
    "term_m1_m3": 0.17,
    "skew": 5.51
  },
  {
    "date": "2025-11-19",
    "atm_iv": 0.70863,
    "iv_rank (HV)": 29.024786025436306,
    "iv_percentile (HV)": 72.84768211920529,
    "term_m1_m2": 2.59,
    "term_m1_m3": -0.46,
    "skew": 8.43
  },
  {
    "date": "2025-11-20",
    "atm_iv": 0.76078,
    "iv_rank (HV)": 32.22008808290979,
    "iv_percentile (HV)": 77.38883632923368,
    "term_m1_m2": 3.05,
    "term_m1_m3": 1.78,
    "skew": 8.15
  },
  {
    "date": "2025-11-21",
    "atm_iv": 0.72988,
    "iv_rank (HV)": 30.326802683563088,
    "iv_percentile (HV)": 74.73982970671712,
    "term_m1_m2": 1.81,
    "term_m1_m3": 0.91,
    "skew": 12.61
  },
  {
    "date": "2025-11-24",
    "atm_iv": 0.687173500351804,
    "iv_rank (HV)": 27.71011685051666,
    "iv_percentile (HV)": 67.29678638941398,
    "term_m1_m2": 0.58,
    "term_m1_m3": -1.66,
    "skew": 5.15
  }
]