[
  {
    "date": "2025-10-31",
    "atm_iv": 0.48905562132714303,
    "iv_rank (HV)": 0.34939495002489035,
    "iv_percentile (HV)": 0.8174409127954361,
    "term_m1_m2": 7.11,
    "term_m1_m3": 10.07,
    "skew": -0.28
  },
  {
    "date": "2025-11-03",
    "atm_iv": 0.5199908287221253,
    "iv_rank (HV)": 0.38289166662365054,
    "iv_percentile (HV)": 0.8403908794788274,
    "term_m1_m2": 9.1,
    "term_m1_m3": 12.76,
    "skew": -2.56
  },
  {
    "date": "2025-11-04",
    "atm_iv": 0.557543295292272,
    "iv_rank (HV)": 0.42355356729313326,
    "iv_percentile (HV)": 0.8991049633848658,
    "term_m1_m2": 11.48,
    "term_m1_m3": 15.7,
    "skew": 0.6
  }
]